[{"open":16.98,"high":18.53,"close":18.53,"low":16.98,"volume":142.0,"price_change":5.66,"p_change":43.98,"ma5":18.53,"ma10":18.53,"ma20":18.53,"v_ma5":142.0,"v_ma10":142.0,"v_ma20":142.0,"turnover":0.09},{"open":20.38,"high":20.38,"close":20.38,"low":20.38,"volume":70.0,"price_change":1.85,"p_change":9.98,"ma5":19.455,"ma10":19.455,"ma20":19.455,"v_ma5":106.0,"v_ma10":106.0,"v_ma20":106.0,"turnover":0.04},{"open":22.42,"high":22.42,"close":22.42,"low":22.42,"volume":43.0,"price_change":2.04,"p_change":10.01,"ma5":20.443,"ma10":20.443,"ma20":20.443,"v_ma5":85.0,"v_ma10":85.0,"v_ma20":85.0,"turnover":0.03},{"open":24.66,"high":24.66,"close":24.66,"low":24.66,"volume":20.01,"price_change":2.24,"p_change":9.99,"ma5":21.498,"ma10":21.498,"ma20":21.498,"v_ma5":68.75,"v_ma10":68.75,"v_ma20":68.75,"turnover":0.01},{"open":27.13,"high":27.13,"close":27.13,"low":27.13,"volume":30.0,"price_change":2.47,"p_change":10.02,"ma5":22.624,"ma10":22.624,"ma20":22.624,"v_ma5":61.0,"v_ma10":61.0,"v_ma20":61.0,"turnover":0.02},{"open":29.84,"high":29.84,"close":29.84,"low":29.84,"volume":56.0,"price_change":2.71,"p_change":9.99,"ma5":24.886,"ma10":23.827,"ma20":23.827,"v_ma5":43.8,"v_ma10":60.17,"v_ma20":60.17,"turnover":0.03},{"open":32.82,"high":32.82,"close":32.82,"low":32.82,"volume":198.95,"price_change":2.98,"p_change":9.99,"ma5":27.374,"ma10":25.111,"ma20":25.111,"v_ma5":69.59,"v_ma10":79.99,"v_ma20":79.99,"turnover":0.12},{"open":36.1,"high":36.1,"close":36.1,"low":36.1,"volume":204.94,"price_change":3.28,"p_change":9.99,"ma5":30.11,"ma10":26.485,"ma20":26.485,"v_ma5":101.98,"v_ma10":95.61,"v_ma20":95.61,"turnover":0.12},{"open":39.71,"high":39.71,"close":39.71,"low":39.71,"volume":914.29,"price_change":3.61,"p_change":10.0,"ma5":33.12,"ma10":27.954,"ma20":27.954,"v_ma5":280.84,"v_ma10":186.58,"v_ma20":186.58,"turnover":0.55},{"open":43.68,"high":43.68,"close":43.68,"low":43.68,"volume":353.6,"price_change":3.97,"p_change":10.0,"ma5":36.43,"ma10":29.527,"ma20":29.527,"v_ma5":345.56,"v_ma10":203.28,"v_ma20":203.28,"turnover":0.21},{"open":48.05,"high":48.05,"close":48.05,"low":48.05,"volume":151.39,"price_change":4.37,"p_change":10.01,"ma5":40.072,"ma10":32.479,"ma20":31.211,"v_ma5":364.63,"v_ma10":204.22,"v_ma20":198.56,"turnover":0.09},{"open":52.86,"high":52.86,"close":52.86,"low":52.86,"volume":151.4,"price_change":4.81,"p_change":10.01,"ma5":44.08,"ma10":35.727,"ma20":33.015,"v_ma5":355.12,"v_ma10":212.36,"v_ma20":194.63,"turnover":0.09},{"open":58.15,"high":58.15,"close":58.15,"low":58.15,"volume":241.3,"price_change":5.29,"p_change":10.01,"ma5":48.49,"ma10":39.3,"ma20":34.948,"v_ma5":362.4,"v_ma10":232.19,"v_ma20":198.22,"turnover":0.14},{"open":63.97,"high":63.97,"close":63.97,"low":63.97,"volume":141.3,"price_change":5.82,"p_change":10.01,"ma5":53.342,"ma10":43.231,"ma20":37.021,"v_ma5":207.8,"v_ma10":244.32,"v_ma20":194.16,"turnover":0.08},{"open":70.37,"high":70.37,"close":70.37,"low":70.37,"volume":398.92,"price_change":6.4,"p_change":10.01,"ma5":58.68,"ma10":47.555,"ma20":39.245,"v_ma5":216.86,"v_ma10":281.21,"v_ma20":207.81,"turnover":0.24},{"open":77.41,"high":77.41,"close":77.41,"low":77.41,"volume":185.45,"price_change":7.04,"p_change":10.0,"ma5":64.552,"ma10":52.312,"ma20":41.63,"v_ma5":223.67,"v_ma10":294.15,"v_ma20":206.41,"turnover":0.11},{"open":85.15,"high":85.15,"close":85.15,"low":85.15,"volume":172.01,"price_change":7.74,"p_change":10.0,"ma5":71.01,"ma10":57.545,"ma20":44.19,"v_ma5":227.8,"v_ma10":291.46,"v_ma20":204.39,"turnover":0.1},{"open":93.67,"high":93.67,"close":93.67,"low":93.67,"volume":191.15,"price_change":8.52,"p_change":10.01,"ma5":78.114,"ma10":63.302,"ma20":46.939,"v_ma5":217.77,"v_ma10":290.08,"v_ma20":203.65,"turnover":0.11},{"open":103.04,"high":103.04,"close":103.04,"low":103.04,"volume":187.15,"price_change":9.37,"p_change":10.0,"ma5":85.928,"ma10":69.635,"ma20":49.892,"v_ma5":226.94,"v_ma10":217.37,"v_ma20":202.78,"turnover":0.11},{"open":113.34,"high":113.34,"close":113.34,"low":113.34,"volume":360.15,"price_change":10.3,"p_change":10.0,"ma5":94.522,"ma10":76.601,"ma20":53.064,"v_ma5":219.18,"v_ma10":218.02,"v_ma20":210.65,"turnover":0.22},{"open":124.67,"high":124.67,"close":124.67,"low":124.67,"volume":1307.24,"price_change":11.33,"p_change":10.0,"ma5":103.974,"ma10":84.263,"ma20":58.371,"v_ma5":443.54,"v_ma10":333.61,"v_ma20":268.91,"turnover":0.78},{"open":137.14,"high":137.14,"close":137.14,"low":137.14,"volume":389.07,"price_change":12.47,"p_change":10.0,"ma5":114.372,"ma10":92.691,"ma20":64.209,"v_ma5":486.95,"v_ma10":357.37,"v_ma20":284.87,"turnover":0.23},{"open":150.85,"high":150.85,"close":150.85,"low":150.85,"volume":355.68,"price_change":13.71,"p_change":10.0,"ma5":125.808,"ma10":101.961,"ma20":70.631,"v_ma5":519.86,"v_ma10":368.81,"v_ma20":300.5,"turnover":0.21},{"open":165.94,"high":165.94,"close":165.94,"low":165.94,"volume":6480.87,"price_change":15.09,"p_change":10.0,"ma5":138.388,"ma10":112.158,"ma20":77.694,"v_ma5":1778.6,"v_ma10":1002.77,"v_ma20":623.54,"turnover":3.89},{"open":182.53,"high":182.53,"close":182.53,"low":150.96,"volume":75317.57,"price_change":16.59,"p_change":10.0,"ma5":152.226,"ma10":123.374,"ma20":85.465,"v_ma5":16770.09,"v_ma10":8494.63,"v_ma20":4387.92,"turnover":45.18},{"open":200.78,"high":200.78,"close":200.78,"low":186.15,"volume":81004.86,"price_change":18.25,"p_change":10.0,"ma5":167.448,"ma10":135.711,"ma20":94.012,"v_ma5":32709.61,"v_ma10":16576.57,"v_ma20":8435.36,"turnover":48.59},{"open":189.0,"high":193.0,"close":180.7,"low":180.7,"volume":53200.6,"price_change":-20.08,"p_change":-10.0,"ma5":176.16,"ma10":145.266,"ma20":101.406,"v_ma5":43271.92,"v_ma10":21879.43,"v_ma20":11085.45,"turnover":31.91},{"open":171.88,"high":181.7,"close":177.5,"low":164.0,"volume":40353.8,"price_change":-3.2,"p_change":-1.77,"ma5":181.49,"ma10":153.649,"ma20":108.476,"v_ma5":51271.54,"v_ma10":25895.7,"v_ma20":13092.89,"turnover":24.21},{"open":171.0,"high":173.02,"close":160.0,"low":159.75,"volume":22768.41,"price_change":-17.5,"p_change":-9.86,"ma5":180.302,"ma10":159.345,"ma20":114.49,"v_ma5":54529.05,"v_ma10":28153.83,"v_ma20":14185.6,"turnover":13.66},{"open":166.0,"high":170.6,"close":166.0,"low":158.38,"volume":30993.26,"price_change":6.0,"p_change":3.75,"ma5":176.996,"ma10":164.611,"ma20":120.606,"v_ma5":45664.19,"v_ma10":31217.14,"v_ma20":15717.58,"turnover":18.59},{"open":162.0,"high":165.0,"close":149.4,"low":149.4,"volume":25842.01,"price_change":-16.6,"p_change":-10.0,"ma5":166.72,"ma10":167.084,"ma20":125.673,"v_ma5":34631.62,"v_ma10":33670.61,"v_ma20":17002.11,"turnover":15.5},{"open":142.1,"high":147.42,"close":143.0,"low":137.48,"volume":23688.42,"price_change":-6.4,"p_change":-4.28,"ma5":159.18,"ma10":167.67,"ma20":130.181,"v_ma5":28729.18,"v_ma10":36000.55,"v_ma20":18178.96,"turnover":14.21},{"open":140.2,"high":157.3,"close":155.97,"low":140.2,"volume":27127.62,"price_change":12.97,"p_change":9.07,"ma5":154.874,"ma10":168.182,"ma20":135.072,"v_ma5":26083.94,"v_ma10":38677.74,"v_ma20":19523.28,"turnover":16.27},{"open":150.13,"high":159.99,"close":157.29,"low":150.11,"volume":18530.99,"price_change":1.32,"p_change":0.85,"ma5":154.332,"ma10":167.317,"ma20":139.738,"v_ma5":25236.46,"v_ma10":39882.75,"v_ma20":20442.76,"turnover":11.12},{"open":159.59,"high":162.96,"close":149.09,"low":148.0,"volume":20931.32,"price_change":-8.2,"p_change":-5.21,"ma5":150.95,"ma10":163.973,"ma20":143.674,"v_ma5":23224.07,"v_ma10":34444.13,"v_ma20":21469.38,"turnover":12.56},{"open":145.5,"high":147.01,"close":134.18,"low":134.18,"volume":25358.41,"price_change":-14.91,"p_change":-10.0,"ma5":147.906,"ma10":157.313,"ma20":146.512,"v_ma5":23127.35,"v_ma10":28879.48,"v_ma20":22728.03,"turnover":15.21},{"open":128.16,"high":141.77,"close":134.8,"low":123.8,"volume":23536.82,"price_change":0.62,"p_change":0.46,"ma5":146.266,"ma10":152.723,"ma20":148.995,"v_ma5":23097.03,"v_ma10":25913.11,"v_ma20":23896.27,"turnover":14.12},{"open":133.0,"high":137.98,"close":137.38,"low":128.88,"volume":12180.73,"price_change":2.58,"p_change":1.91,"ma5":142.548,"ma10":148.711,"ma20":151.18,"v_ma5":20107.65,"v_ma10":23095.8,"v_ma20":24495.75,"turnover":7.31},{"open":134.0,"high":144.01,"close":133.0,"low":132.08,"volume":13514.53,"price_change":-4.38,"p_change":-3.19,"ma5":137.69,"ma10":146.011,"ma20":152.678,"v_ma5":19104.36,"v_ma10":22170.41,"v_ma20":25162.12,"turnover":8.11},{"open":127.5,"high":138.01,"close":123.6,"low":122.28,"volume":10632.77,"price_change":-9.4,"p_change":-7.07,"ma5":132.592,"ma10":141.771,"ma20":153.191,"v_ma5":17044.65,"v_ma10":20134.36,"v_ma20":25675.75,"turnover":6.38},{"open":126.46,"high":135.96,"close":135.96,"low":120.13,"volume":13472.35,"price_change":12.36,"p_change":10.0,"ma5":132.948,"ma10":140.427,"ma20":153.756,"v_ma5":14667.44,"v_ma10":18897.4,"v_ma20":26284.0,"turnover":8.08},{"open":136.5,"high":147.28,"close":138.99,"low":136.0,"volume":18908.57,"price_change":3.03,"p_change":2.23,"ma5":133.786,"ma10":140.026,"ma20":153.848,"v_ma5":13741.79,"v_ma10":18419.41,"v_ma20":27209.98,"turnover":11.34},{"open":139.55,"high":139.55,"close":126.0,"low":125.09,"volume":13551.56,"price_change":-12.99,"p_change":-9.35,"ma5":131.51,"ma10":137.029,"ma20":152.606,"v_ma5":14015.96,"v_ma10":17061.81,"v_ma20":27869.77,"turnover":8.13},{"open":120.5,"high":121.8,"close":113.4,"low":113.4,"volume":13964.01,"price_change":-12.6,"p_change":-10.0,"ma5":127.59,"ma10":132.64,"ma20":149.979,"v_ma5":14105.85,"v_ma10":16605.11,"v_ma20":28243.93,"turnover":8.38},{"open":115.26,"high":115.26,"close":102.06,"low":102.06,"volume":17831.87,"price_change":-11.34,"p_change":-10.0,"ma5":123.282,"ma10":127.937,"ma20":145.955,"v_ma5":15545.67,"v_ma10":16295.16,"v_ma20":25369.65,"turnover":10.7},{"open":96.03,"high":105.35,"close":103.79,"low":91.85,"volume":14607.32,"price_change":1.73,"p_change":1.7,"ma5":116.848,"ma10":124.898,"ma20":141.105,"v_ma5":15772.67,"v_ma10":15220.05,"v_ma20":22049.77,"turnover":8.76},{"open":99.68,"high":108.4,"close":93.41,"low":93.41,"volume":16738.44,"price_change":-10.38,"p_change":-10.0,"ma5":107.732,"ma10":120.759,"ma20":136.741,"v_ma5":15338.64,"v_ma10":14540.22,"v_ma20":20226.66,"turnover":10.04},{"open":88.08,"high":92.97,"close":84.07,"low":84.07,"volume":10994.39,"price_change":-9.34,"p_change":-10.0,"ma5":99.346,"ma10":115.428,"ma20":132.07,"v_ma5":14827.21,"v_ma10":14421.58,"v_ma20":18758.69,"turnover":6.6},{"open":77.0,"high":81.0,"close":75.66,"low":75.66,"volume":13390.05,"price_change":-8.41,"p_change":-10.0,"ma5":91.798,"ma10":109.694,"ma20":127.853,"v_ma5":14712.41,"v_ma10":14409.13,"v_ma20":18289.77,"turnover":8.03},{"open":80.0,"high":82.0,"close":68.09,"low":68.09,"volume":16372.39,"price_change":-7.57,"p_change":-10.01,"ma5":85.004,"ma10":104.143,"ma20":122.957,"v_ma5":14420.52,"v_ma10":14983.09,"v_ma20":17558.73,"turnover":9.82},{"open":62.04,"high":62.04,"close":61.28,"low":61.28,"volume":4127.0,"price_change":-6.81,"p_change":-10.0,"ma5":76.502,"ma10":96.675,"ma20":118.551,"v_ma5":12324.45,"v_ma10":14048.56,"v_ma20":16472.98,"turnover":2.48},{"open":67.41,"high":67.41,"close":67.41,"low":67.41,"volume":257.0,"price_change":6.13,"p_change":10.0,"ma5":71.302,"ma10":89.517,"ma20":114.771,"v_ma5":9028.17,"v_ma10":12183.4,"v_ma20":15301.41,"turnover":0.15},{"open":74.15,"high":74.15,"close":71.8,"low":69.7,"volume":33479.92,"price_change":4.39,"p_change":6.51,"ma5":68.848,"ma10":84.097,"ma20":110.563,"v_ma5":13525.27,"v_ma10":14176.24,"v_ma20":15619.02,"turnover":20.08},{"open":71.8,"high":76.32,"close":72.1,"low":64.62,"volume":29568.86,"price_change":0.3,"p_change":0.42,"ma5":68.136,"ma10":79.967,"ma20":106.303,"v_ma5":16761.03,"v_ma10":15736.72,"v_ma20":16170.92,"turnover":17.74},{"open":72.69,"high":79.31,"close":79.31,"low":72.68,"volume":21583.92,"price_change":7.21,"p_change":10.0,"ma5":70.38,"ma10":77.692,"ma20":102.815,"v_ma5":17803.34,"v_ma10":16111.93,"v_ma20":16203.55,"turnover":12.95},{"open":82.88,"high":87.24,"close":87.24,"low":80.01,"volume":23780.39,"price_change":7.93,"p_change":10.0,"ma5":75.572,"ma10":76.037,"ma20":100.468,"v_ma5":21734.02,"v_ma10":17029.24,"v_ma20":16124.64,"turnover":14.27},{"open":86.98,"high":94.86,"close":91.28,"low":83.01,"volume":19776.23,"price_change":4.04,"p_change":4.63,"ma5":80.346,"ma10":75.824,"ma20":98.292,"v_ma5":25637.86,"v_ma10":17333.02,"v_ma20":15936.62,"turnover":11.86},{"open":92.16,"high":94.5,"close":93.5,"low":88.88,"volume":14676.22,"price_change":2.22,"p_change":2.43,"ma5":84.686,"ma10":76.767,"ma20":96.098,"v_ma5":21877.12,"v_ma10":17701.2,"v_ma20":16061.39,"turnover":8.8},{"open":91.5,"high":102.85,"close":102.85,"low":91.5,"volume":22884.23,"price_change":9.35,"p_change":10.0,"ma5":90.836,"ma10":79.486,"ma20":94.59,"v_ma5":20540.2,"v_ma10":18650.62,"v_ma20":16529.87,"turnover":13.73},{"open":103.33,"high":110.0,"close":100.3,"low":99.0,"volume":23676.91,"price_change":-2.55,"p_change":-2.48,"ma5":95.034,"ma10":82.707,"ma20":93.425,"v_ma5":20958.8,"v_ma10":19381.07,"v_ma20":17182.08,"turnover":14.2},{"open":95.1,"high":104.66,"close":90.27,"low":90.27,"volume":20943.29,"price_change":-10.03,"p_change":-10.0,"ma5":95.64,"ma10":85.606,"ma20":91.141,"v_ma5":20391.38,"v_ma10":21062.7,"v_ma20":17555.63,"turnover":12.56},{"open":82.0,"high":90.3,"close":82.99,"low":81.24,"volume":23994.1,"price_change":-7.28,"p_change":-8.06,"ma5":93.982,"ma10":87.164,"ma20":88.34,"v_ma5":21234.95,"v_ma10":23436.41,"v_ma20":17809.91,"turnover":14.39},{"open":84.06,"high":88.1,"close":87.01,"low":75.0,"volume":20182.59,"price_change":4.02,"p_change":4.84,"ma5":92.684,"ma10":88.685,"ma20":86.391,"v_ma5":22336.22,"v_ma10":22106.67,"v_ma20":18141.46,"turnover":12.11},{"open":85.47,"high":87.99,"close":80.06,"low":79.9,"volume":19944.28,"price_change":-6.95,"p_change":-7.99,"ma5":88.126,"ma10":89.481,"ma20":84.724,"v_ma5":21748.23,"v_ma10":21144.22,"v_ma20":18440.47,"turnover":11.96},{"open":76.5,"high":82.0,"close":78.85,"low":75.11,"volume":12309.02,"price_change":-1.21,"p_change":-1.51,"ma5":83.836,"ma10":89.435,"ma20":83.564,"v_ma5":19474.66,"v_ma10":20216.73,"v_ma20":18164.33,"turnover":7.38},{"open":76.86,"high":76.86,"close":71.5,"low":70.97,"volume":11194.03,"price_change":-7.35,"p_change":-9.32,"ma5":80.082,"ma10":87.861,"ma20":81.949,"v_ma5":17524.8,"v_ma10":18958.09,"v_ma20":17993.66,"turnover":6.72},{"open":71.3,"high":78.65,"close":78.65,"low":71.3,"volume":12573.97,"price_change":7.15,"p_change":10.0,"ma5":79.214,"ma10":86.598,"ma20":81.211,"v_ma5":15240.78,"v_ma10":18237.86,"v_ma20":17785.44,"turnover":7.54},{"open":78.0,"high":82.8,"close":78.72,"low":77.11,"volume":13551.83,"price_change":0.07,"p_change":0.09,"ma5":77.556,"ma10":85.12,"ma20":80.944,"v_ma5":13914.63,"v_ma10":18125.43,"v_ma20":17913.31,"turnover":8.13},{"open":76.3,"high":80.38,"close":78.15,"low":75.98,"volume":8328.09,"price_change":-0.57,"p_change":-0.72,"ma5":77.174,"ma10":82.65,"ma20":81.068,"v_ma5":11591.39,"v_ma10":16669.81,"v_ma20":17660.21,"turnover":5.0},{"open":79.07,"high":84.0,"close":83.21,"low":78.51,"volume":14610.83,"price_change":5.06,"p_change":6.47,"ma5":78.046,"ma10":80.941,"ma20":81.824,"v_ma5":12051.75,"v_ma10":15763.2,"v_ma20":17572.14,"turnover":8.76},{"open":85.5,"high":89.62,"close":88.6,"low":83.08,"volume":14352.27,"price_change":5.39,"p_change":6.48,"ma5":81.466,"ma10":80.774,"ma20":83.19,"v_ma5":12683.4,"v_ma10":15104.1,"v_ma20":18083.4,"turnover":8.61},{"open":88.0,"high":93.29,"close":91.18,"low":87.38,"volume":14429.65,"price_change":2.58,"p_change":2.91,"ma5":83.972,"ma10":81.593,"ma20":84.378,"v_ma5":13054.53,"v_ma10":14147.66,"v_ma20":18792.03,"turnover":8.66},{"open":89.5,"high":91.28,"close":88.8,"low":87.28,"volume":9855.58,"price_change":-2.38,"p_change":-2.61,"ma5":85.988,"ma10":81.772,"ma20":85.228,"v_ma5":12315.28,"v_ma10":13114.95,"v_ma20":17610.81,"turnover":5.91},{"open":87.39,"high":91.83,"close":89.8,"low":86.01,"volume":6926.28,"price_change":1.0,"p_change":1.13,"ma5":88.318,"ma10":82.746,"ma20":86.113,"v_ma5":12034.92,"v_ma10":11813.16,"v_ma20":16478.69,"turnover":4.15},{"open":90.1,"high":91.5,"close":90.61,"low":89.38,"volume":8505.68,"price_change":0.81,"p_change":0.9,"ma5":89.798,"ma10":83.922,"ma20":86.679,"v_ma5":10813.89,"v_ma10":11432.82,"v_ma20":15824.77,"turnover":5.1},{"open":89.8,"high":90.19,"close":89.6,"low":86.48,"volume":6094.54,"price_change":-1.01,"p_change":-1.11,"ma5":89.998,"ma10":85.732,"ma20":86.797,"v_ma5":9162.35,"v_ma10":10922.87,"v_ma20":14940.48,"turnover":3.66},{"open":89.95,"high":92.53,"close":80.64,"low":80.64,"volume":9776.7,"price_change":-8.96,"p_change":-10.0,"ma5":87.89,"ma10":85.931,"ma20":86.265,"v_ma5":8231.76,"v_ma10":10643.15,"v_ma20":14440.5,"turnover":5.86},{"open":78.22,"high":84.88,"close":84.83,"low":73.0,"volume":10435.69,"price_change":4.19,"p_change":5.2,"ma5":87.096,"ma10":86.542,"ma20":85.831,"v_ma5":8347.78,"v_ma10":10331.53,"v_ma20":14228.48,"turnover":6.26},{"open":83.02,"high":85.33,"close":82.5,"low":80.27,"volume":8000.2,"price_change":-2.33,"p_change":-2.75,"ma5":85.636,"ma10":86.977,"ma20":84.813,"v_ma5":8562.56,"v_ma10":10298.74,"v_ma20":13484.28,"turnover":4.8},{"open":80.42,"high":82.28,"close":78.88,"low":78.0,"volume":2964.7,"price_change":-3.62,"p_change":-4.39,"ma5":83.29,"ma10":86.544,"ma20":83.742,"v_ma5":7454.37,"v_ma10":9134.13,"v_ma20":12448.67,"turnover":1.78},{"open":75.03,"high":75.99,"close":70.99,"low":70.99,"volume":3851.0,"price_change":-7.89,"p_change":-10.0,"ma5":79.568,"ma10":84.783,"ma20":82.779,"v_ma5":7005.66,"v_ma10":8084.0,"v_ma20":11594.05,"turnover":2.31},{"open":64.3,"high":67.64,"close":63.89,"low":63.89,"volume":4889.07,"price_change":-7.1,"p_change":-10.0,"ma5":76.218,"ma10":82.054,"ma20":81.824,"v_ma5":6028.13,"v_ma10":7129.94,"v_ma20":10638.8,"turnover":2.93},{"open":62.0,"high":66.0,"close":57.58,"low":57.57,"volume":16493.7,"price_change":-6.31,"p_change":-9.88,"ma5":70.768,"ma10":78.932,"ma20":80.352,"v_ma5":7239.73,"v_ma10":7793.76,"v_ma20":10454.36,"turnover":9.89},{"open":61.0,"high":61.88,"close":59.5,"low":54.0,"volume":10643.74,"price_change":1.92,"p_change":3.33,"ma5":66.168,"ma10":75.902,"ma20":79.324,"v_ma5":7768.44,"v_ma10":8165.5,"v_ma20":9989.33,"turnover":6.38},{"open":61.1,"high":63.5,"close":63.31,"low":59.03,"volume":13311.57,"price_change":3.81,"p_change":6.4,"ma5":63.054,"ma10":73.172,"ma20":78.547,"v_ma5":9837.82,"v_ma10":8646.09,"v_ma20":10039.46,"turnover":7.99},{"open":62.68,"high":62.68,"close":57.89,"low":57.89,"volume":9083.76,"price_change":-5.42,"p_change":-8.56,"ma5":60.434,"ma10":70.001,"ma20":77.867,"v_ma5":10884.37,"v_ma10":8945.01,"v_ma20":9933.94,"turnover":5.45},{"open":57.0,"high":57.68,"close":52.1,"low":52.1,"volume":7138.75,"price_change":-5.79,"p_change":-10.0,"ma5":58.076,"ma10":67.147,"ma20":76.539,"v_ma5":11334.3,"v_ma10":8681.22,"v_ma20":9662.18,"turnover":4.28},{"open":47.7,"high":55.78,"close":51.01,"low":47.58,"volume":12184.2,"price_change":-1.09,"p_change":-2.09,"ma5":56.762,"ma10":63.765,"ma20":75.154,"v_ma5":10472.4,"v_ma10":8856.07,"v_ma20":9593.8,"turnover":7.31},{"open":52.0,"high":54.5,"close":52.8,"low":52.0,"volume":6437.35,"price_change":1.79,"p_change":3.51,"ma5":55.422,"ma10":60.795,"ma20":73.886,"v_ma5":9631.13,"v_ma10":8699.78,"v_ma20":9499.26,"turnover":3.86},{"open":53.2,"high":58.08,"close":58.08,"low":52.02,"volume":10677.45,"price_change":5.28,"p_change":10.0,"ma5":54.376,"ma10":58.715,"ma20":72.63,"v_ma5":9104.3,"v_ma10":9471.06,"v_ma20":9302.59,"turnover":6.41},{"open":60.7,"high":62.69,"close":61.2,"low":59.62,"volume":13896.22,"price_change":3.12,"p_change":5.37,"ma5":55.038,"ma10":57.736,"ma20":71.259,"v_ma5":10066.79,"v_ma10":10475.58,"v_ma20":9279.79,"turnover":8.34},{"open":59.88,"high":61.0,"close":59.18,"low":59.0,"volume":5984.47,"price_change":-2.02,"p_change":-3.3,"ma5":56.454,"ma10":57.265,"ma20":69.66,"v_ma5":9835.94,"v_ma10":10585.12,"v_ma20":8857.53,"turnover":3.59},{"open":59.19,"high":64.45,"close":63.54,"low":53.8,"volume":15537.84,"price_change":4.36,"p_change":7.37,"ma5":58.96,"ma10":57.861,"ma20":68.396,"v_ma5":10506.67,"v_ma10":10489.54,"v_ma20":9141.65,"turnover":9.32},{"open":62.68,"high":66.46,"close":59.1,"low":58.5,"volume":19267.26,"price_change":-4.44,"p_change":-6.99,"ma5":60.22,"ma10":57.821,"ma20":66.862,"v_ma5":13072.65,"v_ma10":11351.89,"v_ma20":9758.69,"turnover":11.56},{"open":55.5,"high":59.49,"close":53.52,"low":53.5,"volume":8429.92,"price_change":-5.58,"p_change":-9.44,"ma5":59.308,"ma10":56.842,"ma20":65.007,"v_ma5":12623.14,"v_ma10":10863.72,"v_ma20":9754.91,"turnover":5.06},{"open":55.46,"high":58.87,"close":58.87,"low":53.2,"volume":10663.31,"price_change":5.35,"p_change":10.0,"ma5":58.842,"ma10":56.94,"ma20":63.471,"v_ma5":11976.56,"v_ma10":11021.68,"v_ma20":9983.35,"turnover":6.4},{"open":59.0,"high":62.0,"close":57.8,"low":57.66,"volume":11600.33,"price_change":-1.07,"p_change":-1.82,"ma5":58.566,"ma10":57.51,"ma20":62.328,"v_ma5":13099.73,"v_ma10":11467.84,"v_ma20":10074.53,"turnover":6.96},{"open":58.3,"high":60.94,"close":60.16,"low":57.0,"volume":8843.16,"price_change":2.36,"p_change":4.08,"ma5":57.89,"ma10":58.425,"ma20":61.095,"v_ma5":11760.8,"v_ma10":11133.73,"v_ma20":9994.9,"turnover":5.3},{"open":57.0,"high":66.18,"close":66.18,"low":57.0,"volume":12710.91,"price_change":6.02,"p_change":10.01,"ma5":59.306,"ma10":59.763,"ma20":60.279,"v_ma5":10449.53,"v_ma10":11761.09,"v_ma20":10230.44,"turnover":7.63},{"open":70.0,"high":72.8,"close":72.8,"low":69.42,"volume":10916.81,"price_change":6.62,"p_change":10.0,"ma5":63.162,"ma10":61.235,"ma20":59.975,"v_ma5":10946.9,"v_ma10":11785.02,"v_ma20":10628.04,"turnover":6.55},{"open":72.8,"high":77.3,"close":74.12,"low":71.0,"volume":22763.56,"price_change":1.32,"p_change":1.81,"ma5":66.212,"ma10":62.527,"ma20":60.132,"v_ma5":13366.95,"v_ma10":12671.76,"v_ma20":11573.67,"turnover":13.66},{"open":74.89,"high":75.9,"close":70.9,"low":69.88,"volume":28583.74,"price_change":-3.22,"p_change":-4.34,"ma5":68.832,"ma10":63.699,"ma20":60.482,"v_ma5":16763.64,"v_ma10":14931.68,"v_ma20":12758.4,"turnover":17.15},{"open":69.5,"high":71.95,"close":66.03,"low":63.9,"volume":16236.77,"price_change":-4.87,"p_change":-6.87,"ma5":70.006,"ma10":63.948,"ma20":60.905,"v_ma5":18242.36,"v_ma10":15001.58,"v_ma20":12745.56,"turnover":9.74},{"open":66.25,"high":72.63,"close":72.63,"low":66.25,"volume":15530.97,"price_change":6.6,"p_change":9.99,"ma5":71.296,"ma10":65.301,"ma20":61.561,"v_ma5":18806.37,"v_ma10":14627.95,"v_ma20":12989.92,"turnover":9.32},{"open":73.0,"high":77.44,"close":74.51,"low":72.11,"volume":22210.88,"price_change":1.88,"p_change":2.59,"ma5":71.638,"ma10":67.4,"ma20":62.121,"v_ma5":21065.18,"v_ma10":16006.04,"v_ma20":13434.88,"turnover":13.32},{"open":75.01,"high":75.45,"close":72.36,"low":70.05,"volume":11786.32,"price_change":-2.15,"p_change":-2.89,"ma5":71.286,"ma10":68.749,"ma20":62.844,"v_ma5":18869.74,"v_ma10":16118.34,"v_ma20":13570.01,"turnover":7.07},{"open":73.35,"high":76.74,"close":76.74,"low":72.68,"volume":268.0,"price_change":4.38,"p_change":6.05,"ma5":72.454,"ma10":70.643,"ma20":64.076,"v_ma5":13206.59,"v_ma10":14985.11,"v_ma20":13226.47,"turnover":0.16},{"open":75.5,"high":77.58,"close":75.35,"low":74.88,"volume":13820.1,"price_change":2.99,"p_change":4.13,"ma5":74.318,"ma10":72.162,"ma20":65.294,"v_ma5":12723.25,"v_ma10":15482.81,"v_ma20":13308.27,"turnover":8.29},{"open":74.55,"high":75.84,"close":75.69,"low":73.9,"volume":14165.33,"price_change":0.34,"p_change":0.45,"ma5":74.93,"ma10":73.113,"ma20":66.438,"v_ma5":12450.13,"v_ma10":15628.25,"v_ma20":13694.67,"turnover":8.5},{"open":76.3,"high":83.0,"close":81.05,"low":76.3,"volume":16953.74,"price_change":5.36,"p_change":7.08,"ma5":76.238,"ma10":73.938,"ma20":67.586,"v_ma5":11398.7,"v_ma10":16231.94,"v_ma20":14008.48,"turnover":10.17},{"open":81.36,"high":83.3,"close":83.02,"low":79.92,"volume":17070.04,"price_change":1.97,"p_change":2.43,"ma5":78.37,"ma10":74.828,"ma20":68.677,"v_ma5":12455.44,"v_ma10":15662.59,"v_ma20":14167.17,"turnover":10.24},{"open":82.79,"high":84.98,"close":80.63,"low":80.62,"volume":13466.34,"price_change":-2.39,"p_change":-2.88,"ma5":79.148,"ma10":75.801,"ma20":69.75,"v_ma5":15095.11,"v_ma10":14150.85,"v_ma20":14541.27,"turnover":8.08},{"open":79.5,"high":84.96,"close":83.92,"low":79.07,"volume":14076.16,"price_change":3.29,"p_change":4.08,"ma5":80.862,"ma10":77.59,"ma20":70.769,"v_ma5":15146.32,"v_ma10":13934.79,"v_ma20":14468.18,"turnover":8.44},{"open":85.0,"high":85.98,"close":84.1,"low":82.03,"volume":13999.4,"price_change":0.18,"p_change":0.21,"ma5":82.544,"ma10":78.737,"ma20":72.019,"v_ma5":15113.14,"v_ma10":13781.63,"v_ma20":14204.79,"turnover":8.4},{"open":83.69,"high":84.78,"close":81.55,"low":79.6,"volume":15037.16,"price_change":-2.55,"p_change":-3.03,"ma5":82.644,"ma10":79.441,"ma20":73.42,"v_ma5":14729.82,"v_ma10":13064.26,"v_ma20":14535.15,"turnover":9.02},{"open":40.95,"high":42.57,"close":42.3,"low":39.99,"volume":34045.59,"price_change":1.52,"p_change":3.73,"ma5":74.5,"ma10":76.435,"ma20":72.592,"v_ma5":18124.93,"v_ma10":15290.19,"v_ma20":15704.27,"turnover":10.21},{"open":42.0,"high":45.88,"close":39.57,"low":39.0,"volume":53990.25,"price_change":-2.73,"p_change":-6.45,"ma5":66.288,"ma10":72.718,"ma20":71.681,"v_ma5":26229.71,"v_ma10":20662.41,"v_ma20":17823.76,"turnover":16.19},{"open":39.95,"high":43.53,"close":43.53,"low":39.7,"volume":56371.04,"price_change":3.96,"p_change":10.01,"ma5":58.21,"ma10":69.536,"ma20":70.849,"v_ma5":34688.69,"v_ma10":24917.5,"v_ma20":20200.16,"turnover":16.91},{"open":46.97,"high":47.88,"close":47.88,"low":45.85,"volume":43755.95,"price_change":4.35,"p_change":9.99,"ma5":50.966,"ma10":66.755,"ma20":69.934,"v_ma5":40640.0,"v_ma10":27876.57,"v_ma20":21752.41,"turnover":13.12},{"open":50.0,"high":52.67,"close":48.01,"low":47.0,"volume":70653.88,"price_change":0.13,"p_change":0.27,"ma5":44.258,"ma10":63.451,"ma20":68.695,"v_ma5":51763.34,"v_ma10":33246.58,"v_ma20":24739.26,"turnover":21.19},{"open":47.49,"high":50.4,"close":49.33,"low":43.3,"volume":48550.98,"price_change":1.32,"p_change":2.75,"ma5":45.664,"ma10":60.082,"ma20":67.455,"v_ma5":54664.42,"v_ma10":36394.67,"v_ma20":26028.63,"turnover":14.56},{"open":47.7,"high":50.0,"close":46.35,"low":45.88,"volume":32649.51,"price_change":-2.98,"p_change":-6.04,"ma5":47.02,"ma10":56.654,"ma20":66.227,"v_ma5":50396.27,"v_ma10":38312.99,"v_ma20":26231.92,"turnover":9.79},{"open":46.74,"high":48.0,"close":46.58,"low":44.57,"volume":27315.4,"price_change":0.23,"p_change":0.5,"ma5":47.63,"ma10":52.92,"ma20":65.255,"v_ma5":44585.14,"v_ma10":39636.92,"v_ma20":26785.85,"turnover":8.19},{"open":46.05,"high":47.14,"close":45.5,"low":44.66,"volume":18904.41,"price_change":-1.08,"p_change":-2.32,"ma5":47.154,"ma10":49.06,"ma20":63.898,"v_ma5":39614.84,"v_ma10":40127.42,"v_ma20":26954.52,"turnover":5.67},{"open":43.52,"high":48.5,"close":47.07,"low":43.52,"volume":31571.68,"price_change":1.57,"p_change":3.45,"ma5":46.966,"ma10":45.612,"ma20":62.526,"v_ma5":31798.4,"v_ma10":41780.87,"v_ma20":27422.56,"turnover":9.47},{"open":46.03,"high":47.48,"close":46.16,"low":45.51,"volume":15676.37,"price_change":-0.91,"p_change":-1.93,"ma5":46.332,"ma10":45.998,"ma20":61.216,"v_ma5":25223.47,"v_ma10":39943.95,"v_ma20":27617.07,"turnover":4.7},{"open":47.05,"high":49.2,"close":48.96,"low":47.05,"volume":28968.35,"price_change":2.8,"p_change":6.07,"ma5":46.854,"ma10":46.937,"ma20":59.828,"v_ma5":24487.24,"v_ma10":37441.76,"v_ma20":29052.08,"turnover":8.69},{"open":49.81,"high":49.88,"close":47.53,"low":46.88,"volume":30329.11,"price_change":-1.43,"p_change":-2.92,"ma5":47.044,"ma10":47.337,"ma20":58.437,"v_ma5":25089.98,"v_ma10":34837.56,"v_ma20":29877.53,"turnover":9.1},{"open":47.56,"high":52.08,"close":50.7,"low":47.53,"volume":30587.96,"price_change":3.17,"p_change":6.67,"ma5":48.084,"ma10":47.619,"ma20":57.187,"v_ma5":27426.69,"v_ma10":33520.77,"v_ma20":30698.67,"turnover":9.17},{"open":50.5,"high":54.83,"close":53.97,"low":48.8,"volume":35719.02,"price_change":3.27,"p_change":6.45,"ma5":49.464,"ma10":48.215,"ma20":55.833,"v_ma5":28256.16,"v_ma10":30027.28,"v_ma20":31636.93,"turnover":10.71},{"open":53.0,"high":56.88,"close":54.58,"low":52.15,"volume":31633.76,"price_change":0.61,"p_change":1.13,"ma5":51.148,"ma10":48.74,"ma20":54.411,"v_ma5":31447.64,"v_ma10":28335.56,"v_ma20":32365.12,"turnover":9.49},{"open":54.0,"high":58.5,"close":57.0,"low":54.0,"volume":44825.92,"price_change":2.42,"p_change":4.43,"ma5":52.756,"ma10":49.805,"ma20":53.23,"v_ma5":34619.15,"v_ma10":29553.2,"v_ma20":33933.1,"turnover":13.45},{"open":56.23,"high":62.7,"close":61.8,"low":52.26,"volume":152902.41,"price_change":4.8,"p_change":8.42,"ma5":55.61,"ma10":51.327,"ma20":52.124,"v_ma5":59133.81,"v_ma10":42111.9,"v_ma20":40874.41,"turnover":45.86},{"open":56.8,"high":59.95,"close":55.62,"low":55.62,"volume":98299.06,"price_change":-6.18,"p_change":-10.0,"ma5":56.594,"ma10":52.339,"ma20":50.7,"v_ma5":72676.03,"v_ma10":50051.36,"v_ma20":45089.39,"turnover":29.48},{"open":51.0,"high":53.7,"close":52.82,"low":51.0,"volume":58205.9,"price_change":-2.8,"p_change":-5.03,"ma5":56.364,"ma10":52.914,"ma20":49.263,"v_ma5":77173.41,"v_ma10":52714.79,"v_ma20":47247.83,"turnover":17.46},{"open":53.21,"high":54.59,"close":50.74,"low":50.4,"volume":53311.01,"price_change":-2.08,"p_change":-3.94,"ma5":55.596,"ma10":53.372,"ma20":49.685,"v_ma5":81508.86,"v_ma10":56478.25,"v_ma20":48211.1,"turnover":15.99},{"open":50.8,"high":51.37,"close":48.18,"low":47.9,"volume":45977.77,"price_change":-2.56,"p_change":-5.04,"ma5":53.832,"ma10":53.294,"ma20":50.116,"v_ma5":81739.23,"v_ma10":58179.19,"v_ma20":47810.47,"turnover":13.79},{"open":48.98,"high":50.15,"close":49.98,"low":48.0,"volume":43139.24,"price_change":1.8,"p_change":3.74,"ma5":51.468,"ma10":53.539,"ma20":50.438,"v_ma5":59786.6,"v_ma10":59460.2,"v_ma20":47148.88,"turnover":12.94},{"open":50.0,"high":52.5,"close":51.6,"low":49.6,"volume":45728.19,"price_change":1.62,"p_change":3.24,"ma5":50.664,"ma10":53.629,"ma20":50.624,"v_ma5":49272.42,"v_ma10":60974.23,"v_ma20":47247.5,"turnover":13.72},{"open":51.69,"high":52.97,"close":51.08,"low":50.5,"volume":39116.88,"price_change":-0.52,"p_change":-1.01,"ma5":50.316,"ma10":53.34,"ma20":50.778,"v_ma5":45454.62,"v_ma10":61314.01,"v_ma20":45670.65,"turnover":11.73}]